{
	"1": ["Начальная... Требуется Advanced-лицензия!", "index.htm"],
	"2": ["1. ... Требуется Advanced-лицензия!", "vkhod.htm"],
	"3": ["2. Админ... Требуется Advanced-лицензия!", "administrator.htm"],
	"4": ["Меню ме... Требуется Advanced-лицензия!", "menyu_menedzherov.htm"],
	"5": ["Усл... Требуется Advanced-лицензия!", "uslugi.htm"],
	"6": ["3.Ме... Требуется Advanced-лицензия!", "3_mendzher.htm"],
	"7": ["Кли... Требуется Advanced-лицензия!", "klienty.htm"],
	"8": ["Зап... Требуется Advanced-лицензия!", "zapis.htm"]
}